eleven_mcp_demo/__init__.py
eleven_mcp_demo-0.1.0.dist-info/METADATA
eleven_mcp_demo-0.1.0.dist-info/WHEEL
eleven_mcp_demo-0.1.0.dist-info/entry_points.txt
eleven_mcp_demo-0.1.0.dist-info/RECORD
