Metadata-Version: 2.4
Name: eleven-mcp-demo
Version: 0.1.0
Summary: Add your description here
Author-email: yupengjun <yu.pengjun@chinaott.net>
Requires-Python: >=3.13
Requires-Dist: mcp[cli]>=1.9.4
